agentscript/__init__.py
agentscript/cli/__main__.py
agentscript/cmd/__init__.py
agentscript/cmd/base.py
agentscript/cmd/invoke.py
agentscript/cmd/parse.py
agentscript/cmd/render.py
agentscript/cmd/use/__init__.py
agentscript/cmd/use/cmd.py
agentscript/db/conn.py
agentscript/db/models.py
agentscript/interpreter.py
agentscript/invoke.py
agentscript/server/models.py
agentscript/server/server.py
agentscript/span.py
agentscript/stream.py
agentscript-0.1.3.dist-info/LICENSE
agentscript-0.1.3.dist-info/METADATA
agentscript-0.1.3.dist-info/WHEEL
agentscript-0.1.3.dist-info/entry_points.txt
agentscript-0.1.3.dist-info/RECORD
