Metadata-Version: 2.1
Name: agentscript
Version: 0.1.3
Summary: A programming language for AI agents
License: Apache 2.0
Author: Patrick Barker
Author-email: patrickbarkerco@gmail.com
Requires-Python: >=3.10,<4.0
Classifier: License :: Other/Proprietary License
Classifier: Programming Language :: Python :: 3
Classifier: Programming Language :: Python :: 3.10
Classifier: Programming Language :: Python :: 3.11
Requires-Dist: agentscript-pyo3 (==0.1.1)
Requires-Dist: fastapi (>=0.110.0,<0.111.0)
Requires-Dist: ipykernel (>=6.29.3,<7.0.0)
Requires-Dist: sqlalchemy (>=2.0.27,<3.0.0)
Requires-Dist: toolfuse (>=0.1.12,<0.2.0)
